{"cookies":[{"name":"_hn_app_session","value":"5c564fe7a221f4328dbf57921c3180f8","domain":"hownowindia.com","path":"/","expires":1700418038.427333,"httpOnly":true,"secure":true,"sameSite":"Lax"},{"name":"hn_session_id","value":"5c564fe7a221f4328dbf57921c3180f8","domain":"hownowindia.com","path":"/","expires":-1,"httpOnly":false,"secure":true,"sameSite":"Lax"},{"name":"browser.timezone","value":"Asia/Kolkata","domain":"hownowindia.com","path":"/","expires":1729362036,"httpOnly":false,"secure":false,"sameSite":"Lax"},{"name":"_hp2_ses_props.3157635180","value":"%7B%22ts%22%3A1697826037241%2C%22d%22%3A%22hownowindia.com%22%2C%22h%22%3A%22%2Fusers%2Fsign_in%22%7D","domain":".hownowindia.com","path":"/","expires":1697827839,"httpOnly":false,"secure":true,"sameSite":"None"},{"name":"hn_session_id","value":"3c3e2698097baca32a2ff3712e2dbb1c","domain":"team.hownowindia.com","path":"/","expires":-1,"httpOnly":false,"secure":true,"sameSite":"Lax"},{"name":"_hn_app_session","value":"3c3e2698097baca32a2ff3712e2dbb1c","domain":".team.hownowindia.com","path":"/","expires":1700418039.730489,"httpOnly":true,"secure":true,"sameSite":"Lax"},{"name":"browser.timezone","value":"Asia/Kolkata","domain":"team.hownowindia.com","path":"/","expires":1729362039,"httpOnly":false,"secure":false,"sameSite":"Lax"},{"name":"_hp2_id.3157635180","value":"%7B%22userId%22%3A%225110322495244609%22%2C%22pageviewId%22%3A%227628211869368989%22%2C%22sessionId%22%3A%227054061547309707%22%2C%22identity%22%3Anull%2C%22trackerVersion%22%3A%224.0%22%7D","domain":".hownowindia.com","path":"/","expires":1731903639,"httpOnly":false,"secure":true,"sameSite":"None"}],"origins":[{"origin":"https://hownowindia.com","localStorage":[{"name":"I18nLocale","value":"en"},{"name":"hnSessionId","value":"5c564fe7a221f4328dbf57921c3180f8"}]},{"origin":"https://team.hownowindia.com","localStorage":[{"name":"I18nLocale","value":"en"},{"name":"hnSessionId","value":"3c3e2698097baca32a2ff3712e2dbb1c"}]}]}